advent_utils/__about__.py
advent_utils/__init__.py
advent_utils/parsers.py
advent_utils/utils.py
advent_utils-0.3.dist-info/METADATA
advent_utils-0.3.dist-info/WHEEL
advent_utils-0.3.dist-info/licenses/LICENSE.txt
advent_utils-0.3.dist-info/RECORD
